polar_llama-0.2.2.dist-info/METADATA
polar_llama-0.2.2.dist-info/WHEEL
polar_llama-0.2.2.dist-info/licenses/LICENSE
polar_llama/__init__.py
polar_llama/expressions.py
polar_llama/polar_llama.pyd
polar_llama/utils.py
polar_llama-0.2.2.dist-info/RECORD
