Metadata-Version: 2.4
Name: polar-llama
Version: 0.2.2
Classifier: Development Status :: 4 - Beta
Classifier: Intended Audience :: Developers
Classifier: Intended Audience :: Science/Research
Classifier: License :: OSI Approved :: MIT License
Classifier: Operating System :: OS Independent
Classifier: Programming Language :: Python :: 3
Classifier: Programming Language :: Python :: 3.8
Classifier: Programming Language :: Python :: 3.9
Classifier: Programming Language :: Python :: 3.10
Classifier: Programming Language :: Python :: 3.11
Classifier: Programming Language :: Python :: 3.12
Classifier: Programming Language :: Python :: Implementation :: CPython
Classifier: Programming Language :: Python :: Implementation :: PyPy
Classifier: Programming Language :: Rust
Classifier: Topic :: Scientific/Engineering :: Artificial Intelligence
Classifier: Topic :: Software Development :: Libraries :: Python Modules
Classifier: Topic :: Database
Classifier: Topic :: Internet :: WWW/HTTP :: Dynamic Content
Classifier: Typing :: Typed
Requires-Dist: requests>=2.32.4
Requires-Dist: pydantic>=2.0.0
Requires-Dist: polars>=1.0.0
License-File: LICENSE
Summary: Parallel inference calls to LLM APIs using Polars dataframes with Pydantic-based structured outputs
Keywords: llm,polars,parallel,inference,ai,openai,anthropic,gemini,groq,bedrock,chatgpt,dataframe,pydantic,structured-outputs,schema-validation
Author-email: David Drummond <daviddrummond95@gmail.com>
License: MIT
Requires-Python: >=3.8
Project-URL: Bug Reports, https://github.com/daviddrummond95/polar_llama/issues
Project-URL: Source, https://github.com/daviddrummond95/polar_llama
Project-URL: Documentation, https://github.com/daviddrummond95/polar_llama#readme
